Metadata-Version: 2.1
Name: quartic-sdk-gsk
Version: 3.13.0
Summary: QuarticSDK is the SDK package which exposes the APIs to the user
Home-page: https://github.com/Quarticai/QuarticSDK/
Author: Quartic.ai engineering team
Author-email: tech@quartic.ai
License: MIT
Keywords: Quartic,QuarticSDK
Platform: UNKNOWN
Classifier: Development Status :: 5 - Production/Stable
Classifier: Intended Audience :: Developers
Classifier: Topic :: Software Development :: Build Tools
Classifier: License :: OSI Approved :: MIT License
Classifier: Programming Language :: Python :: 3.9
License-File: LICENSE
Requires-Dist: aiogqlc (==2.2.0)
Requires-Dist: aiohttp (==3.8.1)
Requires-Dist: aiosignal (==1.3.1)
Requires-Dist: alabaster (==0.7.16)
Requires-Dist: aloe (==0.2.0)
Requires-Dist: ansicolors (==1.1.8)
Requires-Dist: apeye (==1.4.1)
Requires-Dist: apeye-core (==1.1.5)
Requires-Dist: astroid (==2.5.1)
Requires-Dist: asttokens (==2.4.1)
Requires-Dist: async-timeout (==4.0.2)
Requires-Dist: attrs (==22.2.0)
Requires-Dist: autodocsumm (==0.2.12)
Requires-Dist: babel (==2.10.3)
Requires-Dist: beautifulsoup4 (==4.12.3)
Requires-Dist: cachecontrol (==0.12.6)
Requires-Dist: cachetools (==5.2.0)
Requires-Dist: certifi (==2022.12.7)
Requires-Dist: charset-normalizer (==2.0.12)
Requires-Dist: click (==8.0.3)
Requires-Dist: cloudpickle (==1.6.0)
Requires-Dist: colorama (==0.4.6)
Requires-Dist: coloredlogs (==15.0.1)
Requires-Dist: comm (==0.2.2)
Requires-Dist: confluent-kafka (==1.7.0)
Requires-Dist: cssutils (==2.6.0)
Requires-Dist: cycler (==0.12.1)
Requires-Dist: debugpy (==1.8.1)
Requires-Dist: decorator (==5.1.1)
Requires-Dist: dict2css (==0.3.0.post1)
Requires-Dist: docutils (==0.17.1)
Requires-Dist: domdf-python-tools (==3.7.0)
Requires-Dist: entrypoints (==0.4)
Requires-Dist: exceptiongroup (==1.2.0)
Requires-Dist: executing (==1.2.0)
Requires-Dist: frozenlist (==1.3.3)
Requires-Dist: future (==1.0.0)
Requires-Dist: gherkin-official (==4.1.3)
Requires-Dist: google-auth (==2.15.0)
Requires-Dist: html5lib (==1.1)
Requires-Dist: humanfriendly (==10.0)
Requires-Dist: idna (==3.4)
Requires-Dist: imagesize (==1.4.1)
Requires-Dist: importlib-metadata (==7.0.1)
Requires-Dist: iniconfig (==2.0.0)
Requires-Dist: ipykernel (==6.25.2)
Requires-Dist: ipynbname (==2023.2.0.0)
Requires-Dist: ipython (==8.18.1)
Requires-Dist: jedi (==0.19.1)
Requires-Dist: jinja2 (==3.0.3)
Requires-Dist: joblib (==1.3.2)
Requires-Dist: jupyter-client (==7.2.0)
Requires-Dist: jupyter-core (==5.7.2)
Requires-Dist: lazy-object-proxy (==1.10.0)
Requires-Dist: livereload (==2.6.3)
Requires-Dist: lockfile (==0.12.2)
Requires-Dist: lunr (==0.5.8)
Requires-Dist: markupsafe (==2.1.1)
Requires-Dist: matplotlib-inline (==0.1.6)
Requires-Dist: msgpack (==1.0.2)
Requires-Dist: multidict (==6.0.3)
Requires-Dist: natsort (==8.4.0)
Requires-Dist: nest-asyncio (==1.5.4)
Requires-Dist: nltk (==3.6.6)
Requires-Dist: nose (==1.3.7)
Requires-Dist: numpy (==1.22.0)
Requires-Dist: packaging (==20.9)
Requires-Dist: pandas (==1.3.0)
Requires-Dist: parso (==0.8.3)
Requires-Dist: pexpect (==4.8.0)
Requires-Dist: pillow (==9.0.1)
Requires-Dist: platformdirs (==3.7.0)
Requires-Dist: pluggy (==0.13.1)
Requires-Dist: prompt-toolkit (==3.0.43)
Requires-Dist: psutil (==5.9.4)
Requires-Dist: ptyprocess (==0.7.0)
Requires-Dist: pure-eval (==0.2.2)
Requires-Dist: py (==1.11.0)
Requires-Dist: py4j (==0.10.9.7)
Requires-Dist: pyasn1 (==0.4.8)
Requires-Dist: pyasn1-modules (==0.2.8)
Requires-Dist: pydantic (==1.8.2)
Requires-Dist: pygments (==2.17.2)
Requires-Dist: pyodbc (==5.1.0)
Requires-Dist: pyparsing (==2.4.7)
Requires-Dist: pyspark (==3.4.2)
Requires-Dist: pytest (==6.2.2)
Requires-Dist: python-dateutil (==2.8.2)
Requires-Dist: pytz (==2022.7.1)
Requires-Dist: pyyaml (==5.4.1)
Requires-Dist: pyzmq (==22.0.2)
Requires-Dist: regex (==2023.12.25)
Requires-Dist: requests (==2.26.0)
Requires-Dist: rsa (==4.9)
Requires-Dist: ruamel-yaml (==0.17.22)
Requires-Dist: ruamel-yaml-clib (==0.2.8)
Requires-Dist: setuptools (==69.1.0)
Requires-Dist: six (==1.15.0)
Requires-Dist: snowballstemmer (==2.2.0)
Requires-Dist: soupsieve (==2.4.1)
Requires-Dist: sphinx (==3.5.1)
Requires-Dist: sphinx-autoapi (==1.7.0)
Requires-Dist: sphinx-autodoc-typehints (==1.11.1)
Requires-Dist: sphinx-jinja2-compat (==0.2.0)
Requires-Dist: sphinx-prompt (==1.1.0)
Requires-Dist: sphinx-tabs (==3.3.1)
Requires-Dist: sphinx-toolbox (==3.0.0)
Requires-Dist: sphinxcontrib-applehelp (==1.0.4)
Requires-Dist: sphinxcontrib-devhelp (==1.0.2)
Requires-Dist: sphinxcontrib-htmlhelp (==2.0.1)
Requires-Dist: sphinxcontrib-jsmath (==1.0.1)
Requires-Dist: sphinxcontrib-qthelp (==1.0.3)
Requires-Dist: sphinxcontrib-serializinghtml (==1.1.5)
Requires-Dist: stack-data (==0.6.3)
Requires-Dist: tabulate (==0.9.0)
Requires-Dist: tensorflow-io-gcs-filesystem (==0.31.0)
Requires-Dist: toml (==0.10.2)
Requires-Dist: tornado (==6.1)
Requires-Dist: tqdm (==4.66.2)
Requires-Dist: traitlets (==5.14.2)
Requires-Dist: typed-ast (==1.4.2)
Requires-Dist: typing-extensions (==4.6.0)
Requires-Dist: unidecode (==1.3.8)
Requires-Dist: urllib3 (==1.26.6)
Requires-Dist: validators (==0.18.2)
Requires-Dist: wcwidth (==0.2.13)
Requires-Dist: webencodings (==0.5.1)
Requires-Dist: wrapt (==1.12.1)
Requires-Dist: yarl (==1.8.2)
Requires-Dist: zipp (==3.17.0)
Provides-Extra: complete
Requires-Dist: aiogqlc (==2.2.0) ; extra == 'complete'
Requires-Dist: aiohttp (==3.8.1) ; extra == 'complete'
Requires-Dist: aiosignal (==1.3.1) ; extra == 'complete'
Requires-Dist: alabaster (==0.7.16) ; extra == 'complete'
Requires-Dist: aloe (==0.2.0) ; extra == 'complete'
Requires-Dist: ansicolors (==1.1.8) ; extra == 'complete'
Requires-Dist: apeye (==1.4.1) ; extra == 'complete'
Requires-Dist: apeye-core (==1.1.5) ; extra == 'complete'
Requires-Dist: astroid (==2.5.1) ; extra == 'complete'
Requires-Dist: asttokens (==2.4.1) ; extra == 'complete'
Requires-Dist: async-timeout (==4.0.2) ; extra == 'complete'
Requires-Dist: attrs (==22.2.0) ; extra == 'complete'
Requires-Dist: autodocsumm (==0.2.12) ; extra == 'complete'
Requires-Dist: babel (==2.10.3) ; extra == 'complete'
Requires-Dist: beautifulsoup4 (==4.12.3) ; extra == 'complete'
Requires-Dist: cachecontrol (==0.12.6) ; extra == 'complete'
Requires-Dist: cachetools (==5.2.0) ; extra == 'complete'
Requires-Dist: certifi (==2022.12.7) ; extra == 'complete'
Requires-Dist: charset-normalizer (==2.0.12) ; extra == 'complete'
Requires-Dist: click (==8.0.3) ; extra == 'complete'
Requires-Dist: cloudpickle (==1.6.0) ; extra == 'complete'
Requires-Dist: colorama (==0.4.6) ; extra == 'complete'
Requires-Dist: coloredlogs (==15.0.1) ; extra == 'complete'
Requires-Dist: comm (==0.2.2) ; extra == 'complete'
Requires-Dist: confluent-kafka (==1.7.0) ; extra == 'complete'
Requires-Dist: cssutils (==2.6.0) ; extra == 'complete'
Requires-Dist: cycler (==0.12.1) ; extra == 'complete'
Requires-Dist: debugpy (==1.8.1) ; extra == 'complete'
Requires-Dist: decorator (==5.1.1) ; extra == 'complete'
Requires-Dist: dict2css (==0.3.0.post1) ; extra == 'complete'
Requires-Dist: docutils (==0.17.1) ; extra == 'complete'
Requires-Dist: domdf-python-tools (==3.7.0) ; extra == 'complete'
Requires-Dist: entrypoints (==0.4) ; extra == 'complete'
Requires-Dist: exceptiongroup (==1.2.0) ; extra == 'complete'
Requires-Dist: executing (==1.2.0) ; extra == 'complete'
Requires-Dist: frozenlist (==1.3.3) ; extra == 'complete'
Requires-Dist: future (==1.0.0) ; extra == 'complete'
Requires-Dist: gherkin-official (==4.1.3) ; extra == 'complete'
Requires-Dist: google-auth (==2.15.0) ; extra == 'complete'
Requires-Dist: html5lib (==1.1) ; extra == 'complete'
Requires-Dist: humanfriendly (==10.0) ; extra == 'complete'
Requires-Dist: idna (==3.4) ; extra == 'complete'
Requires-Dist: imagesize (==1.4.1) ; extra == 'complete'
Requires-Dist: importlib-metadata (==7.0.1) ; extra == 'complete'
Requires-Dist: iniconfig (==2.0.0) ; extra == 'complete'
Requires-Dist: ipykernel (==6.25.2) ; extra == 'complete'
Requires-Dist: ipynbname (==2023.2.0.0) ; extra == 'complete'
Requires-Dist: ipython (==8.18.1) ; extra == 'complete'
Requires-Dist: jedi (==0.19.1) ; extra == 'complete'
Requires-Dist: jinja2 (==3.0.3) ; extra == 'complete'
Requires-Dist: joblib (==1.3.2) ; extra == 'complete'
Requires-Dist: jupyter-client (==7.2.0) ; extra == 'complete'
Requires-Dist: jupyter-core (==5.7.2) ; extra == 'complete'
Requires-Dist: lazy-object-proxy (==1.10.0) ; extra == 'complete'
Requires-Dist: livereload (==2.6.3) ; extra == 'complete'
Requires-Dist: lockfile (==0.12.2) ; extra == 'complete'
Requires-Dist: lunr (==0.5.8) ; extra == 'complete'
Requires-Dist: markupsafe (==2.1.1) ; extra == 'complete'
Requires-Dist: matplotlib-inline (==0.1.6) ; extra == 'complete'
Requires-Dist: msgpack (==1.0.2) ; extra == 'complete'
Requires-Dist: multidict (==6.0.3) ; extra == 'complete'
Requires-Dist: natsort (==8.4.0) ; extra == 'complete'
Requires-Dist: nest-asyncio (==1.5.4) ; extra == 'complete'
Requires-Dist: nltk (==3.6.6) ; extra == 'complete'
Requires-Dist: nose (==1.3.7) ; extra == 'complete'
Requires-Dist: numpy (==1.22.0) ; extra == 'complete'
Requires-Dist: packaging (==20.9) ; extra == 'complete'
Requires-Dist: pandas (==1.3.0) ; extra == 'complete'
Requires-Dist: parso (==0.8.3) ; extra == 'complete'
Requires-Dist: pexpect (==4.8.0) ; extra == 'complete'
Requires-Dist: pillow (==9.0.1) ; extra == 'complete'
Requires-Dist: platformdirs (==3.7.0) ; extra == 'complete'
Requires-Dist: pluggy (==0.13.1) ; extra == 'complete'
Requires-Dist: prompt-toolkit (==3.0.43) ; extra == 'complete'
Requires-Dist: psutil (==5.9.4) ; extra == 'complete'
Requires-Dist: ptyprocess (==0.7.0) ; extra == 'complete'
Requires-Dist: pure-eval (==0.2.2) ; extra == 'complete'
Requires-Dist: py (==1.11.0) ; extra == 'complete'
Requires-Dist: py4j (==0.10.9.7) ; extra == 'complete'
Requires-Dist: pyasn1 (==0.4.8) ; extra == 'complete'
Requires-Dist: pyasn1-modules (==0.2.8) ; extra == 'complete'
Requires-Dist: pydantic (==1.8.2) ; extra == 'complete'
Requires-Dist: pygments (==2.17.2) ; extra == 'complete'
Requires-Dist: pyodbc (==5.1.0) ; extra == 'complete'
Requires-Dist: pyparsing (==2.4.7) ; extra == 'complete'
Requires-Dist: pyspark (==3.4.2) ; extra == 'complete'
Requires-Dist: pytest (==6.2.2) ; extra == 'complete'
Requires-Dist: python-dateutil (==2.8.2) ; extra == 'complete'
Requires-Dist: pytz (==2022.7.1) ; extra == 'complete'
Requires-Dist: pyyaml (==5.4.1) ; extra == 'complete'
Requires-Dist: pyzmq (==22.0.2) ; extra == 'complete'
Requires-Dist: regex (==2023.12.25) ; extra == 'complete'
Requires-Dist: requests (==2.26.0) ; extra == 'complete'
Requires-Dist: rsa (==4.9) ; extra == 'complete'
Requires-Dist: ruamel-yaml (==0.17.22) ; extra == 'complete'
Requires-Dist: ruamel-yaml-clib (==0.2.8) ; extra == 'complete'
Requires-Dist: setuptools (==69.1.0) ; extra == 'complete'
Requires-Dist: six (==1.15.0) ; extra == 'complete'
Requires-Dist: snowballstemmer (==2.2.0) ; extra == 'complete'
Requires-Dist: soupsieve (==2.4.1) ; extra == 'complete'
Requires-Dist: sphinx (==3.5.1) ; extra == 'complete'
Requires-Dist: sphinx-autoapi (==1.7.0) ; extra == 'complete'
Requires-Dist: sphinx-autodoc-typehints (==1.11.1) ; extra == 'complete'
Requires-Dist: sphinx-jinja2-compat (==0.2.0) ; extra == 'complete'
Requires-Dist: sphinx-prompt (==1.1.0) ; extra == 'complete'
Requires-Dist: sphinx-tabs (==3.3.1) ; extra == 'complete'
Requires-Dist: sphinx-toolbox (==3.0.0) ; extra == 'complete'
Requires-Dist: sphinxcontrib-applehelp (==1.0.4) ; extra == 'complete'
Requires-Dist: sphinxcontrib-devhelp (==1.0.2) ; extra == 'complete'
Requires-Dist: sphinxcontrib-htmlhelp (==2.0.1) ; extra == 'complete'
Requires-Dist: sphinxcontrib-jsmath (==1.0.1) ; extra == 'complete'
Requires-Dist: sphinxcontrib-qthelp (==1.0.3) ; extra == 'complete'
Requires-Dist: sphinxcontrib-serializinghtml (==1.1.5) ; extra == 'complete'
Requires-Dist: stack-data (==0.6.3) ; extra == 'complete'
Requires-Dist: tabulate (==0.9.0) ; extra == 'complete'
Requires-Dist: tensorflow-io-gcs-filesystem (==0.31.0) ; extra == 'complete'
Requires-Dist: toml (==0.10.2) ; extra == 'complete'
Requires-Dist: tornado (==6.1) ; extra == 'complete'
Requires-Dist: tqdm (==4.66.2) ; extra == 'complete'
Requires-Dist: traitlets (==5.14.2) ; extra == 'complete'
Requires-Dist: typed-ast (==1.4.2) ; extra == 'complete'
Requires-Dist: typing-extensions (==4.6.0) ; extra == 'complete'
Requires-Dist: unidecode (==1.3.8) ; extra == 'complete'
Requires-Dist: urllib3 (==1.26.6) ; extra == 'complete'
Requires-Dist: validators (==0.18.2) ; extra == 'complete'
Requires-Dist: wcwidth (==0.2.13) ; extra == 'complete'
Requires-Dist: webencodings (==0.5.1) ; extra == 'complete'
Requires-Dist: wrapt (==1.12.1) ; extra == 'complete'
Requires-Dist: yarl (==1.8.2) ; extra == 'complete'
Requires-Dist: zipp (==3.17.0) ; extra == 'complete'
Requires-Dist: absl-py (==2.1.0) ; extra == 'complete'
Requires-Dist: astunparse (==1.6.3) ; extra == 'complete'
Requires-Dist: cachecontrol[filecache] (==0.12.6) ; extra == 'complete'
Requires-Dist: flatbuffers (==2.0.7) ; extra == 'complete'
Requires-Dist: gast (==0.4.0) ; extra == 'complete'
Requires-Dist: google-pasta (==0.2.0) ; extra == 'complete'
Requires-Dist: grpcio (==1.62.1) ; extra == 'complete'
Requires-Dist: h2o (==3.32.0.4) ; extra == 'complete'
Requires-Dist: h5py (==3.10.0) ; extra == 'complete'
Requires-Dist: keras (==2.7.0) ; extra == 'complete'
Requires-Dist: keras-preprocessing (==1.1.2) ; extra == 'complete'
Requires-Dist: kiwisolver (==1.4.5) ; extra == 'complete'
Requires-Dist: libclang (==18.1.1) ; extra == 'complete'
Requires-Dist: lightgbm (==2.2.2) ; extra == 'complete'
Requires-Dist: markdown (==3.6) ; extra == 'complete'
Requires-Dist: matplotlib (==3.3.4) ; extra == 'complete'
Requires-Dist: numba (==0.60.0) ; extra == 'complete'
Requires-Dist: numexpr (==2.7.2) ; extra == 'complete'
Requires-Dist: onnx (==1.9.0) ; extra == 'complete'
Requires-Dist: opt-einsum (==3.3.0) ; extra == 'complete'
Requires-Dist: pamela (==1.0.0) ; extra == 'complete'
Requires-Dist: patsy (==0.5.1) ; extra == 'complete'
Requires-Dist: plotly (==4.14.3) ; extra == 'complete'
Requires-Dist: protobuf (==3.20.3) ; extra == 'complete'
Requires-Dist: pyaml (==20.4.0) ; extra == 'complete'
Requires-Dist: pycurl (==7.43.0.6) ; extra == 'complete'
Requires-Dist: pynndescent (==0.5.2) ; extra == 'complete'
Requires-Dist: pypmml (==0.9.9) ; extra == 'complete'
Requires-Dist: pytorch-ignite (==0.4.3) ; extra == 'complete'
Requires-Dist: retrying (==1.3.4) ; extra == 'complete'
Requires-Dist: scikit-learn (==1.1.3) ; extra == 'complete'
Requires-Dist: scikit-optimize (==0.8.1) ; extra == 'complete'
Requires-Dist: scipy (==1.7.0) ; extra == 'complete'
Requires-Dist: seaborn (==0.11.1) ; extra == 'complete'
Requires-Dist: statsmodels (==0.12.2) ; extra == 'complete'
Requires-Dist: tbb (==2021.11.0) ; extra == 'complete'
Requires-Dist: tensorboard (==2.16.2) ; extra == 'complete'
Requires-Dist: tensorboard-data-server (==0.7.2) ; extra == 'complete'
Requires-Dist: tensorflow (==2.7.1) ; extra == 'complete'
Requires-Dist: tensorflow-estimator (==2.7.0) ; extra == 'complete'
Requires-Dist: termcolor (==2.4.0) ; extra == 'complete'
Requires-Dist: threadpoolctl (==3.3.0) ; extra == 'complete'
Requires-Dist: torch (==1.7.1) ; extra == 'complete'
Requires-Dist: umap-learn (==0.4.1) ; extra == 'complete'
Requires-Dist: werkzeug (==3.0.1) ; extra == 'complete'
Requires-Dist: wheel (==0.43.0) ; extra == 'complete'
Requires-Dist: xgboost (==0.81) ; extra == 'complete'
